{
  "id": "a8a2d1de-bfbb-4506-8177-18f4087d3bc1",
  "prevId": "507ae601-765a-4ca8-8300-00dd9fab26a4",
  "version": "7",
  "dialect": "postgresql",
  "tables": {
    "public.users": {
      "name": "users",
      "schema": "",
      "columns": {
        "id": {
          "name": "id",
          "type": "uuid",
          "primaryKey": true,
          "notNull": true,
          "default": "gen_random_uuid()"
        },
        "name": {
          "name": "name",
          "type": "varchar(100)",
          "primaryKey": false,
          "notNull": true
        },
        "email": {
          "name": "email",
          "type": "varchar(100)",
          "primaryKey": false,
          "notNull": true
        },
        "password": {
          "name": "password",
          "type": "varchar(60)",
          "primaryKey": false,
          "notNull": true
        },
        "provider": {
          "name": "provider",
          "type": "auth_provider",
          "typeSchema": "public",
          "primaryKey": false,
          "notNull": true,
          "default": "'custom'"
        },
        "is_verified": {
          "name": "is_verified",
          "type": "boolean",
          "primaryKey": false,
          "notNull": true,
          "default": false
        },
        "token_version": {
          "name": "token_version",
          "type": "integer",
          "primaryKey": false,
          "notNull": true,
          "default": 0
        },
        "storage_used": {
          "name": "storage_used",
          "type": "numeric",
          "primaryKey": false,
          "notNull": true,
          "default": "'0'"
        },
        "loop_delay": {
          "name": "loop_delay",
          "type": "integer",
          "primaryKey": false,
          "notNull": true,
          "default": 0
        },
        "created_at": {
          "name": "created_at",
          "type": "timestamp with time zone",
          "primaryKey": false,
          "notNull": true,
          "default": "now()"
        },
        "updated_at": {
          "name": "updated_at",
          "type": "timestamp with time zone",
          "primaryKey": false,
          "notNull": true,
          "default": "now()"
        }
      },
      "indexes": {
        "email_idx": {
          "name": "email_idx",
          "columns": [
            {
              "expression": "email",
              "isExpression": false,
              "asc": true,
              "nulls": "last"
            }
          ],
          "isUnique": true,
          "concurrently": false,
          "method": "btree",
          "with": {}
        }
      },
      "foreignKeys": {},
      "compositePrimaryKeys": {},
      "uniqueConstraints": {},
      "policies": {},
      "checkConstraints": {},
      "isRLSEnabled": false
    },
    "public.users_files": {
      "name": "users_files",
      "schema": "",
      "columns": {
        "id": {
          "name": "id",
          "type": "uuid",
          "primaryKey": true,
          "notNull": true,
          "default": "gen_random_uuid()"
        },
        "user_id": {
          "name": "user_id",
          "type": "uuid",
          "primaryKey": false,
          "notNull": true
        },
        "file_name": {
          "name": "file_name",
          "type": "varchar(255)",
          "primaryKey": false,
          "notNull": true
        },
        "mime_type": {
          "name": "mime_type",
          "type": "varchar(100)",
          "primaryKey": false,
          "notNull": true
        },
        "file_url": {
          "name": "file_url",
          "type": "varchar(2048)",
          "primaryKey": false,
          "notNull": true
        },
        "file_size": {
          "name": "file_size",
          "type": "varchar(30)",
          "primaryKey": false,
          "notNull": true
        },
        "created_at": {
          "name": "created_at",
          "type": "timestamp with time zone",
          "primaryKey": false,
          "notNull": true,
          "default": "now()"
        },
        "updated_at": {
          "name": "updated_at",
          "type": "timestamp with time zone",
          "primaryKey": false,
          "notNull": true,
          "default": "now()"
        }
      },
      "indexes": {},
      "foreignKeys": {
        "users_files_user_id_users_id_fk": {
          "name": "users_files_user_id_users_id_fk",
          "tableFrom": "users_files",
          "tableTo": "users",
          "columnsFrom": [
            "user_id"
          ],
          "columnsTo": [
            "id"
          ],
          "onDelete": "cascade",
          "onUpdate": "no action"
        }
      },
      "compositePrimaryKeys": {},
      "uniqueConstraints": {},
      "policies": {},
      "checkConstraints": {},
      "isRLSEnabled": false
    }
  },
  "enums": {
    "public.auth_provider": {
      "name": "auth_provider",
      "schema": "public",
      "values": [
        "google",
        "custom",
        "github"
      ]
    }
  },
  "schemas": {},
  "sequences": {},
  "roles": {},
  "policies": {},
  "views": {},
  "_meta": {
    "columns": {},
    "schemas": {},
    "tables": {}
  }
}